textfeatures/__init__.py
textfeatures-0.0.2.dist-info/LICENSE
textfeatures-0.0.2.dist-info/METADATA
textfeatures-0.0.2.dist-info/WHEEL
textfeatures-0.0.2.dist-info/top_level.txt
textfeatures-0.0.2.dist-info/RECORD
