Metadata-Version: 2.1
Name: textfeatures
Version: 0.0.2
Summary: A Python package to get basic features from the text data.
Home-page: https://github.com/Amey23/textfeatures
Author: Amey Band
Author-email: ameypband23@gmail.com
License: MIT
Platform: UNKNOWN
Classifier: License :: OSI Approved :: MIT License
Classifier: Programming Language :: Python :: 3.6
Classifier: Programming Language :: Python :: 3.7
Classifier: Programming Language :: Python :: 3.8
Requires-Dist: nltk
